MANIFEST.in
README.txt
setup.cfg
setup.py
src/requires.txt
src/m3_consolequery/__init__.py
src/m3_consolequery/__init__.pyc
src/m3_consolequery/actions.py
src/m3_consolequery/actions.pyc
src/m3_consolequery/app_meta.py
src/m3_consolequery/app_meta.pyc
src/m3_consolequery/forms.py
src/m3_consolequery/forms.pyc
src/m3_consolequery/helpers.py
src/m3_consolequery/helpers.pyc
src/m3_consolequery/models.py
src/m3_consolequery/models.pyc
src/m3_consolequery/version.py
src/m3_consolequery.egg-info/PKG-INFO
src/m3_consolequery.egg-info/SOURCES.txt
src/m3_consolequery.egg-info/dependency_links.txt
src/m3_consolequery.egg-info/top_level.txt
src/m3_consolequery/migrations/0001_initial.py
src/m3_consolequery/migrations/__init__.py
src/m3_consolequery/templates/ui-js/ExtNewQueryWindow.js
src/m3_consolequery/templates/ui-js/ExtQueryConsoleWindow.js
src/tests/__init__.py
src/tests/manage.py
src/tests/prepare_env.py
src/tests/settings.py
src/tests/shell.sh
src/tests/test.sh
src/tests/urls.py
src/tests/version.py
src/tests/core/__init__.py
src/tests/core/tests.py