Metadata-Version: 1.1
Name: m3-consolequery
Version: 1.0.0.2
Summary: Консоль запросов
Home-page: https://bitbucket.org/barsgroup/m3-consolequery
Author: BARS Group
Author-email: bars@bars-open.ru
License: Apache License, Version 2.0
Platform: UNKNOWN
Classifier: Intended Audience :: Developers
Classifier: Environment :: Web Environment
Classifier: Natural Language :: Russian
Classifier: Natural Language :: English
Classifier: Operating System :: OS Independent
Classifier: Programming Language :: Python
Classifier: License :: OSI Approved :: MIT License
Classifier: Development Status :: 5 - Production/Stable
